{
	"SN1962D":{
		"schema":"",
		"name":"SN1962D",
		"sources":[
			{
				"name":"The Open Supernova Catalog",
				"bibcode":"2017ApJ...835...64G",
				"reference":"Guillochon et al. (2017)",
				"secondary":true,
				"url":"https://sne.space",
				"alias":"1"
			}
		],
		"alias":[
			{
				"value":"SN1962D",
				"source":"1"
			}
		],
		"discoverdate":[
			{
				"value":"1962",
				"derived":true,
				"source":"1"
			}
		],
		"errors":[
			{
				"extra":"dec",
				"kind":"bibcode",
				"value":"2012A&A...538A.120L"
			}
		]
	}
}