{
	"SN2008cd":{
		"schema":"",
		"name":"SN2008cd",
		"sources":[
			{
				"name":"2012ApJS..200...12H",
				"bibcode":"2012ApJS..200...12H",
				"reference":"Hicken et al. (2012)",
				"alias":"1"
			},
			{
				"name":"The Open Supernova Catalog",
				"bibcode":"2017ApJ...835...64G",
				"reference":"Guillochon et al. (2017)",
				"secondary":true,
				"url":"https://sne.space",
				"alias":"2"
			}
		],
		"alias":[
			{
				"value":"SN2008cd",
				"source":"1"
			}
		],
		"claimedtype":[
			{
				"value":"Ia",
				"source":"1"
			}
		],
		"discoverdate":[
			{
				"value":"2008/05/01",
				"derived":true,
				"source":"1,2"
			}
		],
		"maxappmag":[
			{
				"value":"16.58",
				"derived":true,
				"source":"1,2"
			}
		],
		"maxband":[
			{
				"value":"i'",
				"derived":true,
				"source":"1,2"
			}
		],
		"maxdate":[
			{
				"value":"2008/05/01",
				"derived":true,
				"source":"1,2"
			}
		],
		"maxvisualappmag":[
			{
				"value":"20.01",
				"derived":true,
				"source":"1,2"
			}
		],
		"maxvisualband":[
			{
				"value":"B",
				"derived":true,
				"source":"1,2"
			}
		],
		"maxvisualdate":[
			{
				"value":"2008/05/01",
				"derived":true,
				"source":"1,2"
			}
		],
		"photometry":[
			{
				"time":"54587.22333",
				"band":"i'",
				"bandset":"Standard",
				"e_magnitude":"0.0220",
				"magnitude":"16.5760",
				"u_time":"MJD",
				"source":"1"
			},
			{
				"time":"54587.22565",
				"band":"r'",
				"bandset":"Standard",
				"e_magnitude":"0.0237",
				"magnitude":"16.8259",
				"u_time":"MJD",
				"source":"1"
			},
			{
				"time":"54587.22796",
				"band":"V",
				"bandset":"Standard",
				"e_magnitude":"0.0739",
				"magnitude":"17.5124",
				"u_time":"MJD",
				"source":"1"
			},
			{
				"time":"54587.23098",
				"band":"B",
				"bandset":"Standard",
				"e_magnitude":"0.1696",
				"magnitude":"20.0114",
				"u_time":"MJD",
				"source":"1"
			},
			{
				"time":"54592.16359",
				"band":"i'",
				"bandset":"Standard",
				"e_magnitude":"0.0545",
				"magnitude":"16.9607",
				"u_time":"MJD",
				"source":"1"
			},
			{
				"time":"54592.16591",
				"band":"r'",
				"bandset":"Standard",
				"e_magnitude":"0.0487",
				"magnitude":"17.2342",
				"u_time":"MJD",
				"source":"1"
			},
			{
				"time":"54592.16824",
				"band":"V",
				"bandset":"Standard",
				"e_magnitude":"0.0630",
				"magnitude":"17.9320",
				"u_time":"MJD",
				"source":"1"
			},
			{
				"time":"54592.17125",
				"band":"B",
				"bandset":"Standard",
				"e_magnitude":"0.2939",
				"magnitude":"20.5773",
				"u_time":"MJD",
				"source":"1"
			},
			{
				"time":"54593.30683",
				"band":"i'",
				"bandset":"Standard",
				"e_magnitude":"0.0249",
				"magnitude":"16.8352",
				"u_time":"MJD",
				"source":"1"
			},
			{
				"time":"54593.30913",
				"band":"r'",
				"bandset":"Standard",
				"e_magnitude":"0.0574",
				"magnitude":"17.2492",
				"u_time":"MJD",
				"source":"1"
			},
			{
				"time":"54593.31146",
				"band":"V",
				"bandset":"Standard",
				"e_magnitude":"0.3155",
				"magnitude":"18.1248",
				"u_time":"MJD",
				"source":"1"
			},
			{
				"time":"54593.31447",
				"band":"B",
				"bandset":"Standard",
				"e_magnitude":"0.3484",
				"magnitude":"20.6905",
				"u_time":"MJD",
				"source":"1"
			},
			{
				"time":"54594.32309",
				"band":"i'",
				"bandset":"Standard",
				"e_magnitude":"0.0312",
				"magnitude":"16.9260",
				"u_time":"MJD",
				"source":"1"
			},
			{
				"time":"54594.32541",
				"band":"r'",
				"bandset":"Standard",
				"e_magnitude":"0.0284",
				"magnitude":"17.3357",
				"u_time":"MJD",
				"source":"1"
			},
			{
				"time":"54594.32774",
				"band":"V",
				"bandset":"Standard",
				"e_magnitude":"0.0916",
				"magnitude":"18.3953",
				"u_time":"MJD",
				"source":"1"
			},
			{
				"time":"54594.33075",
				"band":"B",
				"bandset":"Standard",
				"e_magnitude":"0.3071",
				"magnitude":"20.6603",
				"u_time":"MJD",
				"source":"1"
			},
			{
				"time":"54599.19476",
				"band":"i'",
				"bandset":"Standard",
				"e_magnitude":"0.0257",
				"magnitude":"16.7956",
				"u_time":"MJD",
				"source":"1"
			},
			{
				"time":"54599.19708",
				"band":"r'",
				"bandset":"Standard",
				"e_magnitude":"0.0425",
				"magnitude":"17.4063",
				"u_time":"MJD",
				"source":"1"
			},
			{
				"time":"54599.19937",
				"band":"V",
				"bandset":"Standard",
				"e_magnitude":"0.2655",
				"magnitude":"18.8472",
				"u_time":"MJD",
				"source":"1"
			},
			{
				"time":"54605.20057",
				"band":"i'",
				"bandset":"Standard",
				"e_magnitude":"0.1118",
				"magnitude":"16.8587",
				"u_time":"MJD",
				"source":"1"
			},
			{
				"time":"54605.20288",
				"band":"r'",
				"bandset":"Standard",
				"e_magnitude":"0.0745",
				"magnitude":"18.0878",
				"u_time":"MJD",
				"source":"1"
			},
			{
				"time":"54605.20520",
				"band":"V",
				"bandset":"Standard",
				"e_magnitude":"0.1086",
				"magnitude":"18.8123",
				"u_time":"MJD",
				"source":"1"
			},
			{
				"time":"54617.16830",
				"band":"i'",
				"bandset":"Standard",
				"e_magnitude":"0.1498",
				"magnitude":"17.6645",
				"u_time":"MJD",
				"source":"1"
			},
			{
				"time":"54617.17061",
				"band":"r'",
				"bandset":"Standard",
				"e_magnitude":"0.2218",
				"magnitude":"18.9987",
				"u_time":"MJD",
				"source":"1"
			},
			{
				"time":"54617.17293",
				"band":"V",
				"bandset":"Standard",
				"e_magnitude":"0.2198",
				"magnitude":"19.7236",
				"u_time":"MJD",
				"source":"1"
			},
			{
				"time":"54618.19731",
				"band":"i'",
				"bandset":"Standard",
				"e_magnitude":"0.1002",
				"magnitude":"17.5077",
				"u_time":"MJD",
				"source":"1"
			},
			{
				"time":"54618.19962",
				"band":"r'",
				"bandset":"Standard",
				"e_magnitude":"0.1949",
				"magnitude":"18.9600",
				"u_time":"MJD",
				"source":"1"
			},
			{
				"time":"54618.20193",
				"band":"V",
				"bandset":"Standard",
				"e_magnitude":"0.4395",
				"magnitude":"19.6105",
				"u_time":"MJD",
				"source":"1"
			},
			{
				"time":"54620.21988",
				"band":"i'",
				"bandset":"Standard",
				"e_magnitude":"0.0676",
				"magnitude":"17.7935",
				"u_time":"MJD",
				"source":"1"
			},
			{
				"time":"54620.22219",
				"band":"r'",
				"bandset":"Standard",
				"e_magnitude":"0.2338",
				"magnitude":"18.8507",
				"u_time":"MJD",
				"source":"1"
			},
			{
				"time":"54620.22450",
				"band":"V",
				"bandset":"Standard",
				"e_magnitude":"0.2565",
				"magnitude":"19.6837",
				"u_time":"MJD",
				"source":"1"
			},
			{
				"time":"54622.21378",
				"band":"i'",
				"bandset":"Standard",
				"e_magnitude":"0.1121",
				"magnitude":"17.8224",
				"u_time":"MJD",
				"source":"1"
			},
			{
				"time":"54622.21609",
				"band":"r'",
				"bandset":"Standard",
				"e_magnitude":"0.2052",
				"magnitude":"19.0986",
				"u_time":"MJD",
				"source":"1"
			},
			{
				"time":"54622.21839",
				"band":"V",
				"bandset":"Standard",
				"e_magnitude":"0.2277",
				"magnitude":"19.5839",
				"u_time":"MJD",
				"source":"1"
			}
		]
	}
}