{
	"SN2009js":{
		"schema":"",
		"name":"SN2009js",
		"sources":[
			{
				"name":"2013ApJ...767..166G",
				"bibcode":"2013ApJ...767..166G",
				"reference":"Gandhi et al. (2013)",
				"alias":"1"
			},
			{
				"name":"The Open Supernova Catalog",
				"bibcode":"2017ApJ...835...64G",
				"reference":"Guillochon et al. (2017)",
				"secondary":true,
				"url":"https://sne.space",
				"alias":"2"
			}
		],
		"alias":[
			{
				"value":"SN2009js",
				"source":"1"
			}
		],
		"claimedtype":[
			{
				"value":"II-Pp.",
				"source":"1"
			}
		],
		"discoverdate":[
			{
				"value":"2009/10/13",
				"derived":true,
				"source":"1,2"
			}
		],
		"maxappmag":[
			{
				"value":"15.06",
				"derived":true,
				"source":"1,2"
			}
		],
		"maxband":[
			{
				"value":"I2",
				"derived":true,
				"source":"1,2"
			}
		],
		"maxdate":[
			{
				"value":"2009/10/13",
				"derived":true,
				"source":"1,2"
			}
		],
		"maxvisualappmag":[
			{
				"value":"15.06",
				"derived":true,
				"source":"1,2"
			}
		],
		"maxvisualband":[
			{
				"value":"I2",
				"derived":true,
				"source":"1,2"
			}
		],
		"maxvisualdate":[
			{
				"value":"2009/10/13",
				"derived":true,
				"source":"1,2"
			}
		],
		"photometry":[
			{
				"time":"55117",
				"band":"I1",
				"e_magnitude":"0.11",
				"instrument":"IRAC",
				"magnitude":"15.31",
				"telescope":"Spitzer",
				"u_time":"MJD",
				"source":"1"
			},
			{
				"time":"55117",
				"band":"I2",
				"e_magnitude":"0.11",
				"instrument":"IRAC",
				"magnitude":"15.06",
				"telescope":"Spitzer",
				"u_time":"MJD",
				"source":"1"
			}
		]
	}
}