{
	"SN2004dx":{
		"schema":"",
		"name":"SN2004dx",
		"sources":[
			{
				"name":"2004ATel..348....1S",
				"bibcode":"2004ATel..348....1S",
				"reference":"Soderberg, Frail, & Kulkarni (2004)",
				"alias":"1"
			},
			{
				"name":"The Open Supernova Catalog",
				"bibcode":"2017ApJ...835...64G",
				"reference":"Guillochon et al. (2017)",
				"secondary":true,
				"url":"https://sne.space",
				"alias":"2"
			}
		],
		"alias":[
			{
				"value":"SN2004dx",
				"source":"1"
			}
		],
		"discoverdate":[
			{
				"value":"2004",
				"derived":true,
				"source":"2"
			}
		],
		"photometry":[
			{
				"time":"53306.2",
				"fluxdensity":"78.0",
				"frequency":"8.4851",
				"instrument":"VLA",
				"u_fluxdensity":"µJy",
				"u_frequency":"GHz",
				"u_time":"MJD",
				"upperlimit":true,
				"source":"1"
			}
		]
	}
}